CHANGELOG.md
dok8s/cli/__main__.py
dok8s/cli/base_command.py
dok8s/cli/commands/__init__.py
dok8s/cli/commands/component.py
dok8s/cli/commands/docker.py
dok8s/cli/commands/kubernetes.py
dok8s/cli/commands/resource.py
dok8s/lib/analyses/__init__.py
dok8s/lib/analyses/component_analysis.py
dok8s/lib/analyses/docker_analysis.py
dok8s/lib/analyses/kubernetes_analyser.py
dok8s/lib/analyses/resource_analysis.py
dok8s/lib/base_analyser.py
dok8s/lib/helpers/component_loader.py
dok8s/logger.py
dok8s/settings.py
dok8s-0.0.4.dist-info/entry_points.txt
dok8s-0.0.4.dist-info/LICENSE
dok8s-0.0.4.dist-info/WHEEL
dok8s-0.0.4.dist-info/METADATA
dok8s-0.0.4.dist-info/RECORD
