Metadata-Version: 2.1
Name: dok8s
Version: 0.0.4
Summary: Output notes for a Kubernetes deployment
Home-page: https://github.com/nichelia/dok8s
License: MIT
Keywords: python,kubernetes,notes,documentation
Author: Nicholas Elia
Author-email: me@nichelia.com
Maintainer: Nicholas Elia
Maintainer-email: me@nichelia.com
Requires-Python: >=3.7,<4.0
Classifier: License :: OSI Approved :: MIT License
Classifier: Programming Language :: Python :: 3
Classifier: Programming Language :: Python :: 3.7
Classifier: Programming Language :: Python :: 3.8
Requires-Dist: kubernetes (>=11.0,<12.0)
Requires-Dist: pyyaml (>=5.3,<6.0)
Requires-Dist: tabulate (>=0.8,<0.9)
Project-URL: Repository, https://github.com/nichelia/dok8s
